TagsParameters/__init__.py
TagsParameters/tagsparameters.py
TagsParameters/tagsparser.py
robotframework_tags_parameters-0.0.4.dist-info/METADATA
robotframework_tags_parameters-0.0.4.dist-info/WHEEL
robotframework_tags_parameters-0.0.4.dist-info/top_level.txt
robotframework_tags_parameters-0.0.4.dist-info/RECORD
