Metadata-Version: 2.1
Name: robotframework-tags-parameters
Version: 0.0.4
Summary: Can use and parse parameters from robotframework test tags
Home-page: https://github.com/LeConTesteur/robotframework-tags-parameters
Author: LeConTesteur
Project-URL: Bug Tracker, https://github.com/LeConTesteur/robotframework-tags-parameters/issues
Keywords: robotframework,tags,argparse,parsing,jsonschema,data validation,validation
Classifier: License :: OSI Approved :: GNU General Public License v3 or later (GPLv3+)
Requires-Python: >=3.8
Requires-Dist: robotframework
Requires-Dist: robotframework-jsonlibrary
Requires-Dist: pyaml
Requires-Dist: argparse-from-jsonschema >=0.0.5
Provides-Extra: tests
Requires-Dist: requests-mock ; extra == 'tests'
Requires-Dist: flake8 ; extra == 'tests'
Requires-Dist: coverage ; extra == 'tests'
